venvr/__init__.py
venvr/agent.py
venvr/builder.py
venvr/cli.py
venvr/config.py
venvr/manager.py
venvr/runner.py
venvr/templates.py
venvr/util.py
venvr/venvr.py
venvr-0.1.5.8.dist-info/LICENSE
venvr-0.1.5.8.dist-info/METADATA
venvr-0.1.5.8.dist-info/WHEEL
venvr-0.1.5.8.dist-info/entry_points.txt
venvr-0.1.5.8.dist-info/top_level.txt
venvr-0.1.5.8.dist-info/RECORD
